Experiments/Lab_A/RevCounter/RevCounter.srcs/sources_1/new/RevCounter.v
module RevCounter( 
    input wire clk,
    input wire rst,
    input wire s,
    output reg [15:0] cnt = 0,
    output wire Rc
);

    always @(posedge clk) begin
        if (rst) begin
            cnt <= 16'd0;
        end else if (s == 1'b0) begin
            cnt <= cnt + 1'b1;          // 自增，16'hFFFF 自动回绕至 16'h0
        end else begin
            cnt <= cnt - 1'b1;          // 自减，16'h0 自动回绕至 16'hFFFF
        end
    end

    // 组合逻辑输出进位/借位信号
    assign Rc = (s == 1'b0 && cnt == 16'hFFFF) ||
                (s == 1'b1 && cnt == 16'h0000);

endmodule

Experiments/Lab_A/RevCounter/RevCounter.srcs/sim_1/new/RevCounter_tb.v
`timescale 1ns / 1ps

module RevCounter_tb();

    reg clk;
    reg rst;
    reg s;
    wire [15:0] cnt;
    wire Rc;

    // 实例化待测模块
    RevCounter uut (
        .clk(clk),
        .rst(rst),
        .s(s),
        .cnt(cnt),
        .Rc(Rc)
    );

    // 时钟生成：周期 10ns
    always #5 clk = ~clk;

    initial begin
        // 初始化
        clk = 0;
        rst = 0;
        s   = 0;

        // 1. 测试同步复位
        rst = 1;
        #10;                        // 第一个时钟上升沿，复位生效
        rst = 0;
        #10;
        $display("After reset: cnt = %h, Rc = %b", cnt, Rc);

        // 2. 自增测试（s=0）
        s = 0;
        // 计数几个周期
        repeat(20) #10;
        $display("After 20 inc cycles: cnt = %h, Rc = %b", cnt, Rc);

        // 3. 自减测试（s=1）
        s = 1;
        repeat(5) #10;
        $display("After 5 dec cycles: cnt = %h, Rc = %b", cnt, Rc);

        // 4. 边界测试：从 0 自减
        s = 1;
        // 手动设置为0
        rst = 1; #10; rst = 0;
        #10;                        // cnt=0, s=1 -> Rc应为1
        $display("cnt=0, s=1 -> cnt = %h, Rc = %b", cnt, Rc);
        #10;                        // 执行一次自减，cnt应该变为FFFF
        $display("After dec from 0: cnt = %h, Rc = %b", cnt, Rc);

        // 5. 边界测试：从 FFFF 自增
        s = 0;
        // 手动设置为FFFF：先自减到FFFF，然后切s=0
        s = 1;                      // 减模式
        // 从0减一次到FFFF，当前cnt=0，减一次
        #10;                        // cnt=0 -> FFFF
        s = 0;                      // 切回增模式
        #10;                        // 现在cnt=FFFF, s=0，Rc应为1
        $display("cnt=FFFF, s=0 -> cnt = %h, Rc = %b", cnt, Rc);
        #10;                        // 自增，cnt变为0000
        $display("After inc from FFFF: cnt = %h, Rc = %b", cnt, Rc);

        // 6. 动态切换方向
        s = 0;
        repeat(3) #10;              // 增3次
        s = 1;
        repeat(2) #10;              // 减2次
        $display("After direction change: cnt = %h, Rc = %b", cnt, Rc);

        #50 $finish;
    end

    // 波形输出（VCD）
    initial begin
        $dumpfile("RevCounter_tb.vcd");
        $dumpvars(0, RevCounter_tb);
    end

endmodule

Experiments/Lab_A/RevCounter/RevCounter.sim/sim_1/behav/xsim/RevCounter_tb.vcd
$date
   Thu May 21 12:32:42 2026
$end
$version
  2020.2
$end
$timescale
  1ps
$end
$scope module RevCounter_tb $end
$var reg 1 ! clk $end
$var reg 1 " rst $end
$var reg 1 # s $end
$var wire 16 $ cnt [15:0] $end
$var wire 1 % Rc $end
$scope module uut $end
$var wire 1 & clk $end
$var wire 1 ' rst $end
$var wire 1 ( s $end
$var reg 16 ) cnt [15:0] $end
$var wire 1 % Rc $end
$upscope $end
$upscope $end
$enddefinitions $end
#0
$dumpvars
0!
1"
0#
b0 $
0%
0&
1'
0(
b0 )
$end
#5000
1!
1&
b0 )
#10000
0!
0"
0&
0'
#15000
1!
b1 $
1&
b1 )
#20000
0!
0&
#25000
1!
b10 $
1&
b10 )
#30000
0!
0&
#35000
1!
b11 $
1&
b11 )
#40000
0!
0&
#45000
1!
b100 $
1&
b100 )
#50000
0!
0&
#55000
1!
b101 $
1&
b101 )
#60000
0!
0&
#65000
1!
b110 $
1&
b110 )
#70000
0!
0&
#75000
1!
b111 $
1&
b111 )
#80000
0!
0&
#85000
1!
b1000 $
1&
b1000 )
#90000
0!
0&
#95000
1!
b1001 $
1&
b1001 )
#100000
0!
0&
#105000
1!
b1010 $
1&
b1010 )
#110000
0!
0&
#115000
1!
b1011 $
1&
b1011 )
#120000
0!
0&
#125000
1!
b1100 $
1&
b1100 )
#130000
0!
0&
#135000
1!
b1101 $
1&
b1101 )
#140000
0!
0&
#145000
1!
b1110 $
1&
b1110 )
#150000
0!
0&
#155000
1!
b1111 $
1&
b1111 )
#160000
0!
0&
#165000
1!
b10000 $
1&
b10000 )
#170000
0!
0&
#175000
1!
b10001 $
1&
b10001 )
#180000
0!
0&
#185000
1!
b10010 $
1&
b10010 )
#190000
0!
0&
#195000
1!
b10011 $
1&
b10011 )
#200000
0!
0&
#205000
1!
b10100 $
1&
b10100 )
#210000
0!
0&
#215000
1!
b10101 $
1&
b10101 )
#220000
0!
1#
0&
1(
#225000
1!
b10100 $
1&
b10100 )
#230000
0!
0&
#235000
1!
b10011 $
1&
b10011 )
#240000
0!
0&
#245000
1!
b10010 $
1&
b10010 )
#250000
0!
0&
#255000
1!
b10001 $
1&
b10001 )
#260000
0!
0&
#265000
1!
b10000 $
1&
b10000 )
#270000
0!
1"
0&
1'
#275000
1!
b0 $
1%
1&
b0 )
#280000
0!
0"
0&
0'
#285000
1!
b1111111111111111 $
0%
1&
b1111111111111111 )
#290000
0!
0&
#295000
1!
b1111111111111110 $
1&
b1111111111111110 )
#300000
0!
1#
0&
1(
#305000
1!
b1111111111111101 $
1&
b1111111111111101 )
#310000
0!
0#
0&
0(
#315000
1!
b1111111111111110 $
1&
b1111111111111110 )
#320000
0!
0&
#325000
1!
b1111111111111111 $
1%
1&
b1111111111111111 )
#330000
0!
0&
#335000
1!
b0 $
0%
1&
b0 )
#340000
0!
0&
#345000
1!
b1 $
1&
b1 )
#350000
0!
0&
#355000
1!
b10 $
1&
b10 )
#360000
0!
1#
0&
1(
#365000
1!
b1 $
1&
b1 )
#370000
0!
0&
#375000
1!
b0 $
1%
1&
b0 )
#380000
0!
0&
#385000
1!
b1111111111111111 $
0%
1&
b1111111111111111 )
#390000
0!
0&
#395000
1!
b1111111111111110 $
1&
b1111111111111110 )
#400000
0!
0&
#405000
1!
b1111111111111101 $
1&
b1111111111111101 )
#410000
0!
0&
#415000
1!
b1111111111111100 $
1&
b1111111111111100 )
#420000
0!
0&
#425000
1!
b1111111111111011 $
1&
b1111111111111011 )
